beancount_portfolio_allocation/__init__.py
beancount_portfolio_allocation/allocation.py
beancount_portfolio_allocation/allocation_report.py
beancount_portfolio_allocation/loader.py
beancount_portfolio_allocation-0.3.0.dist-info/METADATA
beancount_portfolio_allocation-0.3.0.dist-info/RECORD
beancount_portfolio_allocation-0.3.0.dist-info/WHEEL
beancount_portfolio_allocation-0.3.0.dist-info/entry_points.txt
beancount_portfolio_allocation-0.3.0.dist-info/top_level.txt
tests/__init__.py
tests/missing_prices_test.py
tests/no_operating_currency_test.py
tests/valid_reports_test.py
tests/zero_position_test.py
