Metadata-Version: 2.1
Name: beancount-portfolio-allocation
Version: 0.3.0
Summary: Beancount portfolio allocation report
Home-page: https://github.com/ghislainbourgeois/beancount_portfolio_allocation/
Author: Ghislain Bourgeois
Author-email: ghislain.bourgeois@gmail.com
License: GPLv2
Keywords: beancount report portfolio allocation
Platform: UNKNOWN
Classifier: Programming Language :: Python :: 3
Classifier: License :: OSI Approved :: GNU General Public License v2 (GPLv2)
Classifier: Operating System :: OS Independent
Classifier: Environment :: Console
Classifier: Intended Audience :: End Users/Desktop
Classifier: Intended Audience :: Financial and Insurance Industry
Classifier: Topic :: Office/Business :: Financial
Classifier: Topic :: Office/Business :: Financial :: Accounting
Classifier: Topic :: Office/Business :: Financial :: Investment
Requires-Dist: beancount (>=2.1.2)
Requires-Dist: tabulate
